systolic_env/systolic_scheduler.v
/*********************************************************************************
  Systolic Array Scheduler for 4x4 Matrix Multiplication
**********************************************************************************
* DESCRIPTION:
*   This module implements a data scheduler for a 4x4 systolic array processor
*   used in matrix multiplication. It generates the proper timing and sequencing
*   to feed matrix elements in a diagonal wave pattern, ensuring optimal 
*   utilization of processing elements.
*
* OPERATION:
*   - Takes two 4x4 input matrices (A and B) as flattened inputs
*   - Feeds data to systolic array in 7 sequential steps (0-6)
*   - Each row is offset by one step to create diagonal data flow
*   - Configurable delay between feeding steps for timing control
*
* INTERFACES:
*   - start: Initiates feeding sequence
*   - valid: Indicates when output data is valid
*   - done: Asserted when complete feeding sequence is finished
*   - a_out[0:3], b_out[0:3]: Data streams to systolic array rows
*
* PARAMETERS:
*   - DELAY: Clock cycles between each feeding step (default: 10)
*   - DATA_WIDTH: Bit width of matrix elements (default: 32)
*
* AUTHOR: [ZeuzoxD]
******************************************************************************************/

module systolic_scheduler#(
  parameter DELAY = 10,
  parameter DATA_WIDTH = 32
) (
  input clk,
  input rst,
  input start,

  input [DATA_WIDTH-1:0] mat_a_00, mat_a_01, mat_a_02, mat_a_03,
  input [DATA_WIDTH-1:0] mat_a_10, mat_a_11, mat_a_12, mat_a_13,
  input [DATA_WIDTH-1:0] mat_a_20, mat_a_21, mat_a_22, mat_a_23,
  input [DATA_WIDTH-1:0] mat_a_30, mat_a_31, mat_a_32, mat_a_33,

  input [DATA_WIDTH-1:0] mat_b_00, mat_b_01, mat_b_02, mat_b_03,
  input [DATA_WIDTH-1:0] mat_b_10, mat_b_11, mat_b_12, mat_b_13,
  input [DATA_WIDTH-1:0] mat_b_20, mat_b_21, mat_b_22, mat_b_23,
  input [DATA_WIDTH-1:0] mat_b_30, mat_b_31, mat_b_32, mat_b_33,

  output reg [DATA_WIDTH-1:0] a_out0, a_out1, a_out2, a_out3,
  output reg [DATA_WIDTH-1:0] b_out0, b_out1, b_out2, b_out3,

  output reg valid,
  output reg done
);

  reg [3:0] step; //Current feeding step (0-6)
  reg [$clog2(DELAY+1)-1:0] delay_counter; //Delay timing counter
  reg feeding; //Feeding state flag

  wire [DATA_WIDTH-1:0] mat_a [0:3][0:3];
  wire [DATA_WIDTH-1:0] mat_b [0:3][0:3];

  assign mat_a[0][0] = mat_a_00; assign mat_a[0][1] = mat_a_01; assign mat_a[0][2] = mat_a_02; assign mat_a[0][3] = mat_a_03;
  assign mat_a[1][0] = mat_a_10; assign mat_a[1][1] = mat_a_11; assign mat_a[1][2] = mat_a_12; assign mat_a[1][3] = mat_a_13;
  assign mat_a[2][0] = mat_a_20; assign mat_a[2][1] = mat_a_21; assign mat_a[2][2] = mat_a_22; assign mat_a[2][3] = mat_a_23;
  assign mat_a[3][0] = mat_a_30; assign mat_a[3][1] = mat_a_31; assign mat_a[3][2] = mat_a_32; assign mat_a[3][3] = mat_a_33;

  assign mat_b[0][0] = mat_b_00; assign mat_b[0][1] = mat_b_01; assign mat_b[0][2] = mat_b_02; assign mat_b[0][3] = mat_b_03;
  assign mat_b[1][0] = mat_b_10; assign mat_b[1][1] = mat_b_11; assign mat_b[1][2] = mat_b_12; assign mat_b[1][3] = mat_b_13;
  assign mat_b[2][0] = mat_b_20; assign mat_b[2][1] = mat_b_21; assign mat_b[2][2] = mat_b_22; assign mat_b[2][3] = mat_b_23;
  assign mat_b[3][0] = mat_b_30; assign mat_b[3][1] = mat_b_31; assign mat_b[3][2] = mat_b_32; assign mat_b[3][3] = mat_b_33;

  always @(posedge clk or posedge rst) begin
    if (rst) begin
      step <= 0;
      delay_counter <= 0;
      valid <= 0;
      done <= 0;
      feeding <= 0;
      a_out0 <= 0; a_out1 <= 0; a_out2 <= 0; a_out3 <= 0;
      b_out0 <= 0; b_out1 <= 0; b_out2 <= 0; b_out3 <= 0;
    end else begin

    // Start condition: Begin feeding when start asserted and system is idle
    if (start && !feeding && !done) begin
        feeding <= 1;
        step <= 0;
        delay_counter <= 0;
        done <= 0;
        valid <= 0;
      end

      if (feeding) begin
        // Delay timer: Controls feeding rate
        if (delay_counter == DELAY-1) begin
            delay_counter <= 0;
            valid <= 1;
            /***************************************************************
               * Systolic Data Feeding Pattern
               * Each row feeds during a 4-step window, offset by row number
            ***************************************************************/
            // Row 0: Active during steps 0,1,2,3
            if (step <= 3) begin
              a_out0 <= mat_a[0][step];
              b_out0 <= mat_b[step][0];
            end else begin
              a_out0 <= 0;
              b_out0 <= 0;
            end

            // Row 1: Active during steps 1,2,3,4 (offset +1)
            if (step >= 1 && step <= 4) begin
              a_out1 <= mat_a[1][step-1];
              b_out1 <= mat_b[step-1][1];
            end else begin
              a_out1 <= 0;
              b_out1 <= 0;
            end

            // Row 2: Active during steps 2,3,4,5 (offset +2)
            if (step >= 2 && step <= 5) begin
              a_out2 <= mat_a[2][step-2];
              b_out2 <= mat_b[step-2][2];
            end else begin
              a_out2 <= 0;  
              b_out2 <= 0;
            end

            // Row 3: Active during steps 3,4,5,6 (offset +3)
            if (step >= 3 && step <= 6) begin
              a_out3 <= mat_a[3][step-3];
              b_out3 <= mat_b[step-3][3];
            end else begin
              a_out3 <= 0;
              b_out3 <= 0;
            end

            // Sequence completion: Done after step 6 is processed
            if (step == 7) begin
              feeding <= 0;
              done <= 1;
              valid <= 0;
            end else begin
              step <= step + 1;
            end

        end else begin
          delay_counter <= delay_counter + 1;
          valid <= 0;
        end
      end else if (done) begin
          valid <= 0;
          if (start) begin
              done <= 0; //clear done when starting new operation
          end
      end else begin
        // Idle state 
        valid <= 0;
      end
    end
  end
endmodule

src/scheduler_tb.v
/*********************************************************************************
  Testbench for Systolic Array Scheduler
**********************************************************************************
* DESCRIPTION:
*   Comprehensive testbench for 4x4 systolic array scheduler module.
*   Tests diagonal wave feeding pattern, timing control, and system states.
*
* TEST COVERAGE:
*   - Basic feeding sequence with pattern verification
*   - Reset during operation handling
*   - Back-to-back operations with proper done/start handshake
*
* AUTHOR: [ZeuzoxD]
******************************************************************************************/

module tb_systolic_scheduler();

    parameter DELAY = 10;
    parameter DATA_WIDTH = 32;
    parameter CLK_PERIOD = 10;

    reg clk, rst, start;
    
    reg [DATA_WIDTH-1:0] mat_a_00, mat_a_01, mat_a_02, mat_a_03;
    reg [DATA_WIDTH-1:0] mat_a_10, mat_a_11, mat_a_12, mat_a_13;
    reg [DATA_WIDTH-1:0] mat_a_20, mat_a_21, mat_a_22, mat_a_23;
    reg [DATA_WIDTH-1:0] mat_a_30, mat_a_31, mat_a_32, mat_a_33;
    
    reg [DATA_WIDTH-1:0] mat_b_00, mat_b_01, mat_b_02, mat_b_03;
    reg [DATA_WIDTH-1:0] mat_b_10, mat_b_11, mat_b_12, mat_b_13;
    reg [DATA_WIDTH-1:0] mat_b_20, mat_b_21, mat_b_22, mat_b_23;
    reg [DATA_WIDTH-1:0] mat_b_30, mat_b_31, mat_b_32, mat_b_33;
    
    wire [DATA_WIDTH-1:0] a_out0, a_out1, a_out2, a_out3;
    wire [DATA_WIDTH-1:0] b_out0, b_out1, b_out2, b_out3;
    wire valid, done;

    integer cycle_count, valid_count, error_count;
    
    // Expected output verification arrays: [output_port][step]
    reg [DATA_WIDTH-1:0] expected_a_out [0:3][0:6];
    reg [DATA_WIDTH-1:0] expected_b_out [0:3][0:6];

    systolic_scheduler #(
        .DELAY(DELAY),
        .DATA_WIDTH(DATA_WIDTH)
    ) dut (
        .clk(clk), .rst(rst), .start(start),
        .mat_a_00(mat_a_00), .mat_a_01(mat_a_01), .mat_a_02(mat_a_02), .mat_a_03(mat_a_03),
        .mat_a_10(mat_a_10), .mat_a_11(mat_a_11), .mat_a_12(mat_a_12), .mat_a_13(mat_a_13),
        .mat_a_20(mat_a_20), .mat_a_21(mat_a_21), .mat_a_22(mat_a_22), .mat_a_23(mat_a_23),
        .mat_a_30(mat_a_30), .mat_a_31(mat_a_31), .mat_a_32(mat_a_32), .mat_a_33(mat_a_33),
        .mat_b_00(mat_b_00), .mat_b_01(mat_b_01), .mat_b_02(mat_b_02), .mat_b_03(mat_b_03),
        .mat_b_10(mat_b_10), .mat_b_11(mat_b_11), .mat_b_12(mat_b_12), .mat_b_13(mat_b_13),
        .mat_b_20(mat_b_20), .mat_b_21(mat_b_21), .mat_b_22(mat_b_22), .mat_b_23(mat_b_23),
        .mat_b_30(mat_b_30), .mat_b_31(mat_b_31), .mat_b_32(mat_b_32), .mat_b_33(mat_b_33),
        .a_out0(a_out0), .a_out1(a_out1), .a_out2(a_out2), .a_out3(a_out3),
        .b_out0(b_out0), .b_out1(b_out1), .b_out2(b_out2), .b_out3(b_out3),
        .valid(valid), .done(done)
    );

    initial begin
        clk = 0;
        forever #(CLK_PERIOD/2) clk = ~clk;
    end

    task init_matrices;
        begin
            mat_a_00 = 32'h01; mat_a_01 = 32'h02; mat_a_02 = 32'h03; mat_a_03 = 32'h04;
            mat_a_10 = 32'h05; mat_a_11 = 32'h06; mat_a_12 = 32'h07; mat_a_13 = 32'h08;
            mat_a_20 = 32'h09; mat_a_21 = 32'h0A; mat_a_22 = 32'h0B; mat_a_23 = 32'h0C;
            mat_a_30 = 32'h0D; mat_a_31 = 32'h0E; mat_a_32 = 32'h0F; mat_a_33 = 32'h10;
            
            mat_b_00 = 32'h11; mat_b_01 = 32'h12; mat_b_02 = 32'h13; mat_b_03 = 32'h14;
            mat_b_10 = 32'h15; mat_b_11 = 32'h16; mat_b_12 = 32'h17; mat_b_13 = 32'h18;
            mat_b_20 = 32'h19; mat_b_21 = 32'h1A; mat_b_22 = 32'h1B; mat_b_23 = 32'h1C;
            mat_b_30 = 32'h1D; mat_b_31 = 32'h1E; mat_b_32 = 32'h1F; mat_b_33 = 32'h20;
        end
    endtask

    /***************************************************************
     * Calculate expected diagonal feeding pattern
     * Row N feeds during steps N through N+3 (4 elements each)
     ***************************************************************/
    task calculate_expected;
        integer step, port;
        begin
            for (step = 0; step <= 6; step = step + 1) begin
                for (port = 0; port <= 3; port = port + 1) begin
                    expected_a_out[port][step] = 0;
                    expected_b_out[port][step] = 0;
                end
            end
            
            // Row 0: steps 0,1,2,3
            expected_a_out[0][0] = mat_a_00; expected_b_out[0][0] = mat_b_00;
            expected_a_out[0][1] = mat_a_01; expected_b_out[0][1] = mat_b_10;
            expected_a_out[0][2] = mat_a_02; expected_b_out[0][2] = mat_b_20;
            expected_a_out[0][3] = mat_a_03; expected_b_out[0][3] = mat_b_30;
            
            // Row 1: steps 1,2,3,4 (offset +1)
            expected_a_out[1][1] = mat_a_10; expected_b_out[1][1] = mat_b_01;
            expected_a_out[1][2] = mat_a_11; expected_b_out[1][2] = mat_b_11;
            expected_a_out[1][3] = mat_a_12; expected_b_out[1][3] = mat_b_21;
            expected_a_out[1][4] = mat_a_13; expected_b_out[1][4] = mat_b_31;
            
            // Row 2: steps 2,3,4,5 (offset +2)
            expected_a_out[2][2] = mat_a_20; expected_b_out[2][2] = mat_b_02;
            expected_a_out[2][3] = mat_a_21; expected_b_out[2][3] = mat_b_12;
            expected_a_out[2][4] = mat_a_22; expected_b_out[2][4] = mat_b_22;
            expected_a_out[2][5] = mat_a_23; expected_b_out[2][5] = mat_b_32;
            
            // Row 3: steps 3,4,5,6 (offset +3)
            expected_a_out[3][3] = mat_a_30; expected_b_out[3][3] = mat_b_03;
            expected_a_out[3][4] = mat_a_31; expected_b_out[3][4] = mat_b_13;
            expected_a_out[3][5] = mat_a_32; expected_b_out[3][5] = mat_b_23;
            expected_a_out[3][6] = mat_a_33; expected_b_out[3][6] = mat_b_33;
        end
    endtask

    task check_outputs;
        input integer step;
        begin
            if (valid) begin
                $display("Step %0d - Checking outputs:", step);
                
                if (a_out0 !== expected_a_out[0][step]) begin
                    $display("ERROR: a_out0 mismatch at step %0d. Expected: %h, Got: %h", 
                             step, expected_a_out[0][step], a_out0);
                    error_count = error_count + 1;
                end
                if (a_out1 !== expected_a_out[1][step]) begin
                    $display("ERROR: a_out1 mismatch at step %0d. Expected: %h, Got: %h", 
                             step, expected_a_out[1][step], a_out1);
                    error_count = error_count + 1;
                end
                if (a_out2 !== expected_a_out[2][step]) begin
                    $display("ERROR: a_out2 mismatch at step %0d. Expected: %h, Got: %h", 
                             step, expected_a_out[2][step], a_out2);
                    error_count = error_count + 1;
                end
                if (a_out3 !== expected_a_out[3][step]) begin
                    $display("ERROR: a_out3 mismatch at step %0d. Expected: %h, Got: %h", 
                             step, expected_a_out[3][step], a_out3);
                    error_count = error_count + 1;
                end
                
                if (b_out0 !== expected_b_out[0][step]) begin
                    $display("ERROR: b_out0 mismatch at step %0d. Expected: %h, Got: %h", 
                             step, expected_b_out[0][step], b_out0);
                    error_count = error_count + 1;
                end
                if (b_out1 !== expected_b_out[1][step]) begin
                    $display("ERROR: b_out1 mismatch at step %0d. Expected: %h, Got: %h", 
                             step, expected_b_out[1][step], b_out1);
                    error_count = error_count + 1;
                end
                if (b_out2 !== expected_b_out[2][step]) begin
                    $display("ERROR: b_out2 mismatch at step %0d. Expected: %h, Got: %h", 
                             step, expected_b_out[2][step], b_out2);
                    error_count = error_count + 1;
                end
                if (b_out3 !== expected_b_out[3][step]) begin
                    $display("ERROR: b_out3 mismatch at step %0d. Expected: %h, Got: %h", 
                             step, expected_b_out[3][step], b_out3);
                    error_count = error_count + 1;
                end
                
                $display("  A_out: %h %h %h %h", a_out0, a_out1, a_out2, a_out3);
                $display("  B_out: %h %h %h %h", b_out0, b_out1, b_out2, b_out3);
            end
        end
    endtask

    initial begin
        $display("Starting Systolic Scheduler Testbench");
        $display("DELAY = %0d, DATA_WIDTH = %0d", DELAY, DATA_WIDTH);
        
        cycle_count = 0;
        valid_count = 0;
        error_count = 0;
        
        rst = 1;
        start = 0;
        init_matrices();
        calculate_expected();
        
        repeat(5) @(posedge clk);
        rst = 0;
        repeat(2) @(posedge clk);
        
        $display("\n=== Test 1: Basic Operation ===");
        
        start = 1;
        @(posedge clk);
        start = 0;
        
        // Monitor 7 feeding steps
        begin : monitor_loop1
            repeat(7 * DELAY + 20) begin
                @(posedge clk);
                cycle_count = cycle_count + 1;
                
                if (valid) begin
                    check_outputs(valid_count);
                    valid_count = valid_count + 1;
                end
                
                if (done) begin
                    $display("Done signal asserted at cycle %0d", cycle_count);
                    disable monitor_loop1;
                end
            end
        end
        
        if (valid_count !== 7) begin
            $display("ERROR: Expected 7 valid cycles, got %0d", valid_count);
            error_count = error_count + 1;
        end
        
        $display("\n=== Test 2: Reset During Operation ===");
        
        start = 1;
        @(posedge clk);
        start = 0;
        
        repeat(3 * DELAY) @(posedge clk);
        rst = 1;
        @(posedge clk);
        rst = 0;
        @(posedge clk);
        
        if (valid !== 0 || done !== 0) begin
            $display("ERROR: valid or done not cleared after reset");
            error_count = error_count + 1;
        end
        
        $display("\n=== Test 3: Back-to-back Operations ===");
        
        start = 1;
        @(posedge clk);
        start = 0;
        $display("Started first operation");
        
        wait(done);
        $display("First operation completed, done=%b", done);
        @(posedge clk);
        
        // Acknowledge completion: pulse start to clear done flag
        $display("Acknowledging completion with done=%b", done);
        start = 1;
        @(posedge clk);
        start = 0;
        $display("After acknowledgment: done=%b", done);
        
        wait(!done);
        @(posedge clk);
        
        $display("Starting second operation with done=%b", done);
        start = 1;
        @(posedge clk);
        $display("After start pulse: done=%b, feeding=%b", done, dut.feeding);
        start = 0;
        
        valid_count = 0;
        begin : monitor_loop2
            repeat(7 * DELAY + 10) begin
                @(posedge clk);
                if (valid) valid_count = valid_count + 1;
                if (done) disable monitor_loop2;
            end
        end
        
        if (valid_count !== 7) begin
            $display("ERROR: Back-to-back operation failed. Expected 7 valid cycles, got %0d", valid_count);
            error_count = error_count + 1;
        end
        
        $display("\n=== Test Summary ===");
        if (error_count == 0) begin
            $display("✓ All tests PASSED!");
        end else begin
            $display("✗ %0d errors found", error_count);
        end
        
        $display("Total simulation cycles: %0d", cycle_count);
        $finish;
    end

    // Simulation timeout protection
    initial begin
        #(CLK_PERIOD * 1000);
        $display("ERROR: Simulation timeout!");
        $finish;
    end

    initial begin
        $dumpfile("systolic_scheduler.vcd");
        $dumpvars(0, tb_systolic_scheduler);
    end

endmodule

src/systolic_scheduler.vcd
$date
	Mon Jun  9 19:45:15 2025
$end
$version
	Icarus Verilog
$end
$timescale
	1s
$end
$scope module tb_systolic_scheduler $end
$var wire 1 ! valid $end
$var wire 1 " done $end
$var wire 32 # b_out3 [31:0] $end
$var wire 32 $ b_out2 [31:0] $end
$var wire 32 % b_out1 [31:0] $end
$var wire 32 & b_out0 [31:0] $end
$var wire 32 ' a_out3 [31:0] $end
$var wire 32 ( a_out2 [31:0] $end
$var wire 32 ) a_out1 [31:0] $end
$var wire 32 * a_out0 [31:0] $end
$var parameter 32 + CLK_PERIOD $end
$var parameter 32 , DATA_WIDTH $end
$var parameter 32 - DELAY $end
$var reg 1 . clk $end
$var reg 32 / mat_a_00 [31:0] $end
$var reg 32 0 mat_a_01 [31:0] $end
$var reg 32 1 mat_a_02 [31:0] $end
$var reg 32 2 mat_a_03 [31:0] $end
$var reg 32 3 mat_a_10 [31:0] $end
$var reg 32 4 mat_a_11 [31:0] $end
$var reg 32 5 mat_a_12 [31:0] $end
$var reg 32 6 mat_a_13 [31:0] $end
$var reg 32 7 mat_a_20 [31:0] $end
$var reg 32 8 mat_a_21 [31:0] $end
$var reg 32 9 mat_a_22 [31:0] $end
$var reg 32 : mat_a_23 [31:0] $end
$var reg 32 ; mat_a_30 [31:0] $end
$var reg 32 < mat_a_31 [31:0] $end
$var reg 32 = mat_a_32 [31:0] $end
$var reg 32 > mat_a_33 [31:0] $end
$var reg 32 ? mat_b_00 [31:0] $end
$var reg 32 @ mat_b_01 [31:0] $end
$var reg 32 A mat_b_02 [31:0] $end
$var reg 32 B mat_b_03 [31:0] $end
$var reg 32 C mat_b_10 [31:0] $end
$var reg 32 D mat_b_11 [31:0] $end
$var reg 32 E mat_b_12 [31:0] $end
$var reg 32 F mat_b_13 [31:0] $end
$var reg 32 G mat_b_20 [31:0] $end
$var reg 32 H mat_b_21 [31:0] $end
$var reg 32 I mat_b_22 [31:0] $end
$var reg 32 J mat_b_23 [31:0] $end
$var reg 32 K mat_b_30 [31:0] $end
$var reg 32 L mat_b_31 [31:0] $end
$var reg 32 M mat_b_32 [31:0] $end
$var reg 32 N mat_b_33 [31:0] $end
$var reg 1 O rst $end
$var reg 1 P start $end
$var integer 32 Q cycle_count [31:0] $end
$var integer 32 R error_count [31:0] $end
$var integer 32 S valid_count [31:0] $end
$scope module dut $end
$var wire 1 . clk $end
$var wire 32 T mat_a_00 [31:0] $end
$var wire 32 U mat_a_01 [31:0] $end
$var wire 32 V mat_a_02 [31:0] $end
$var wire 32 W mat_a_03 [31:0] $end
$var wire 32 X mat_a_10 [31:0] $end
$var wire 32 Y mat_a_11 [31:0] $end
$var wire 32 Z mat_a_12 [31:0] $end
$var wire 32 [ mat_a_13 [31:0] $end
$var wire 32 \ mat_a_20 [31:0] $end
$var wire 32 ] mat_a_21 [31:0] $end
$var wire 32 ^ mat_a_22 [31:0] $end
$var wire 32 _ mat_a_23 [31:0] $end
$var wire 32 ` mat_a_30 [31:0] $end
$var wire 32 a mat_a_31 [31:0] $end
$var wire 32 b mat_a_32 [31:0] $end
$var wire 32 c mat_a_33 [31:0] $end
$var wire 32 d mat_b_00 [31:0] $end
$var wire 32 e mat_b_01 [31:0] $end
$var wire 32 f mat_b_02 [31:0] $end
$var wire 32 g mat_b_03 [31:0] $end
$var wire 32 h mat_b_10 [31:0] $end
$var wire 32 i mat_b_11 [31:0] $end
$var wire 32 j mat_b_12 [31:0] $end
$var wire 32 k mat_b_13 [31:0] $end
$var wire 32 l mat_b_20 [31:0] $end
$var wire 32 m mat_b_21 [31:0] $end
$var wire 32 n mat_b_22 [31:0] $end
$var wire 32 o mat_b_23 [31:0] $end
$var wire 32 p mat_b_30 [31:0] $end
$var wire 32 q mat_b_31 [31:0] $end
$var wire 32 r mat_b_32 [31:0] $end
$var wire 32 s mat_b_33 [31:0] $end
$var wire 1 O rst $end
$var wire 1 P start $end
$var parameter 32 t DATA_WIDTH $end
$var parameter 32 u DELAY $end
$var reg 32 v a_out0 [31:0] $end
$var reg 32 w a_out1 [31:0] $end
$var reg 32 x a_out2 [31:0] $end
$var reg 32 y a_out3 [31:0] $end
$var reg 32 z b_out0 [31:0] $end
$var reg 32 { b_out1 [31:0] $end
$var reg 32 | b_out2 [31:0] $end
$var reg 32 } b_out3 [31:0] $end
$var reg 4 ~ delay_counter [3:0] $end
$var reg 1 " done $end
$var reg 1 !" feeding $end
$var reg 4 "" step [3:0] $end
$var reg 1 ! valid $end
$upscope $end
$scope begin monitor_loop1 $end
$upscope $end
$scope begin monitor_loop2 $end
$upscope $end
$scope task calculate_expected $end
$var integer 32 #" port [31:0] $end
$var integer 32 $" step [31:0] $end
$upscope $end
$scope task check_outputs $end
$var integer 32 %" step [31:0] $end
$upscope $end
$scope task init_matrices $end
$upscope $end
$upscope $end
$enddefinitions $end
$comment Show the parameter values. $end
$dumpall
b1010 u
b100000 t
b1010 -
b100000 ,
b1010 +
$end
#0
$dumpvars
bx %"
b111 $"
b100 #"
b0 ""
0!"
b0 ~
b0 }
b0 |
b0 {
b0 z
b0 y
b0 x
b0 w
b0 v
b100000 s
b11111 r
b11110 q
b11101 p
b11100 o
b11011 n
b11010 m
b11001 l
b11000 k
b10111 j
b10110 i
b10101 h
b10100 g
b10011 f
b10010 e
b10001 d
b10000 c
b1111 b
b1110 a
b1101 `
b1100 _
b1011 ^
b1010 ]
b1001 \
b1000 [
b111 Z
b110 Y
b101 X
b100 W
b11 V
b10 U
b1 T
b0 S
b0 R
b0 Q
0P
1O
b100000 N
b11111 M
b11110 L
b11101 K
b11100 J
b11011 I
b11010 H
b11001 G
b11000 F
b10111 E
b10110 D
b10101 C
b10100 B
b10011 A
b10010 @
b10001 ?
b10000 >
b1111 =
b1110 <
b1101 ;
b1100 :
b1011 9
b1010 8
b1001 7
b1000 6
b111 5
b110 4
b101 3
b100 2
b11 1
b10 0
b1 /
0.
b0 *
b0 )
b0 (
b0 '
b0 &
b0 %
b0 $
b0 #
0"
0!
$end
#5
1.
#10
0.
#15
1.
#20
0.
#25
1.
#30
0.
#35
1.
#40
0.
#45
0O
1.
#50
0.
#55
1.
#60
0.
#65
1!"
1P
1.
#70
0.
#75
b1 ~
0P
1.
#80
0.
#85
b10 ~
b1 Q
1.
#90
0.
#95
b11 ~
b10 Q
1.
#100
0.
#105
b100 ~
b11 Q
1.
#110
0.
#115
b101 ~
b100 Q
1.
#120
0.
#125
b110 ~
b101 Q
1.
#130
0.
#135
b111 ~
b110 Q
1.
#140
0.
#145
b1000 ~
b111 Q
1.
#150
0.
#155
b1001 ~
b1000 Q
1.
#160
0.
#165
b1 ""
b10001 &
b10001 z
b1 *
b1 v
1!
b0 ~
b1001 Q
1.
#170
0.
#175
0!
b1 ~
b1 S
b0 %"
b1010 Q
1.
#180
0.
#185
b10 ~
b1011 Q
1.
#190
0.
#195
b11 ~
b1100 Q
1.
#200
0.
#205
b100 ~
b1101 Q
1.
#210
0.
#215
b101 ~
b1110 Q
1.
#220
0.
#225
b110 ~
b1111 Q
1.
#230
0.
#235
b111 ~
b10000 Q
1.
#240
0.
#245
b1000 ~
b10001 Q
1.
#250
0.
#255
b1001 ~
b10010 Q
1.
#260
0.
#265
b10 ""
b10010 %
b10010 {
b101 )
b101 w
b10101 &
b10101 z
b10 *
b10 v
1!
b0 ~
b10011 Q
1.
#270
0.
#275
0!
b1 ~
b10 S
b1 %"
b10100 Q
1.
#280
0.
#285
b10 ~
b10101 Q
1.
#290
0.
#295
b11 ~
b10110 Q
1.
#300
0.
#305
b100 ~
b10111 Q
1.
#310
0.
#315
b101 ~
b11000 Q
1.
#320
0.
#325
b110 ~
b11001 Q
1.
#330
0.
#335
b111 ~
b11010 Q
1.
#340
0.
#345
b1000 ~
b11011 Q
1.
#350
0.
#355
b1001 ~
b11100 Q
1.
#360
0.
#365
b11 ""
b10011 $
b10011 |
b1001 (
b1001 x
b10110 %
b10110 {
b110 )
b110 w
b11001 &
b11001 z
b11 *
b11 v
1!
b0 ~
b11101 Q
1.
#370
0.
#375
0!
b1 ~
b11 S
b10 %"
b11110 Q
1.
#380
0.
#385
b10 ~
b11111 Q
1.
#390
0.
#395
b11 ~
b100000 Q
1.
#400
0.
#405
b100 ~
b100001 Q
1.
#410
0.
#415
b101 ~
b100010 Q
1.
#420
0.
#425
b110 ~
b100011 Q
1.
#430
0.
#435
b111 ~
b100100 Q
1.
#440
0.
#445
b1000 ~
b100101 Q
1.
#450
0.
#455
b1001 ~
b100110 Q
1.
#460
0.
#465
b100 ""
b10100 #
b10100 }
b1101 '
b1101 y
b10111 $
b10111 |
b1010 (
b1010 x
b11010 %
b11010 {
b111 )
b111 w
b11101 &
b11101 z
b100 *
b100 v
1!
b0 ~
b100111 Q
1.
#470
0.
#475
0!
b1 ~
b100 S
b11 %"
b101000 Q
1.
#480
0.
#485
b10 ~
b101001 Q
1.
#490
0.
#495
b11 ~
b101010 Q
1.
#500
0.
#505
b100 ~
b101011 Q
1.
#510
0.
#515
b101 ~
b101100 Q
1.
#520
0.
#525
b110 ~
b101101 Q
1.
#530
0.
#535
b111 ~
b101110 Q
1.
#540
0.
#545
b1000 ~
b101111 Q
1.
#550
0.
#555
b1001 ~
b110000 Q
1.
#560
0.
#565
b101 ""
b11000 #
b11000 }
b1110 '
b1110 y
b11011 $
b11011 |
b1011 (
b1011 x
b11110 %
b11110 {
b1000 )
b1000 w
b0 &
b0 z
b0 *
b0 v
1!
b0 ~
b110001 Q
1.
#570
0.
#575
0!
b1 ~
b101 S
b100 %"
b110010 Q
1.
#580
0.
#585
b10 ~
b110011 Q
1.
#590
0.
#595
b11 ~
b110100 Q
1.
#600
0.
#605
b100 ~
b110101 Q
1.
#610
0.
#615
b101 ~
b110110 Q
1.
#620
0.
#625
b110 ~
b110111 Q
1.
#630
0.
#635
b111 ~
b111000 Q
1.
#640
0.
#645
b1000 ~
b111001 Q
1.
#650
0.
#655
b1001 ~
b111010 Q
1.
#660
0.
#665
b110 ""
b11100 #
b11100 }
b1111 '
b1111 y
b11111 $
b11111 |
b1100 (
b1100 x
b0 %
b0 {
b0 )
b0 w
1!
b0 ~
b111011 Q
1.
#670
0.
#675
0!
b1 ~
b110 S
b101 %"
b111100 Q
1.
#680
0.
#685
b10 ~
b111101 Q
1.
#690
0.
#695
b11 ~
b111110 Q
1.
#700
0.
#705
b100 ~
b111111 Q
1.
#710
0.
#715
b101 ~
b1000000 Q
1.
#720
0.
#725
b110 ~
b1000001 Q
1.
#730
0.
#735
b111 ~
b1000010 Q
1.
#740
0.
#745
b1000 ~
b1000011 Q
1.
#750
0.
#755
b1001 ~
b1000100 Q
1.
#760
0.
#765
b111 ""
b100000 #
b100000 }
b10000 '
b10000 y
b0 $
b0 |
b0 (
b0 x
1!
b0 ~
b1000101 Q
1.
#770
0.
#775
0!
b1 ~
b111 S
b110 %"
b1000110 Q
1.
#780
0.
#785
b10 ~
b1000111 Q
1.
#790
0.
#795
b11 ~
b1001000 Q
1.
#800
0.
#805
b100 ~
b1001001 Q
1.
#810
0.
#815
b101 ~
b1001010 Q
1.
#820
0.
#825
b110 ~
b1001011 Q
1.
#830
0.
#835
b111 ~
b1001100 Q
1.
#840
0.
#845
b1000 ~
b1001101 Q
1.
#850
0.
#855
b1001 ~
b1001110 Q
1.
#860
0.
#865
1"
0!"
b0 #
b0 }
b0 '
b0 y
0!
b0 ~
b1001111 Q
1.
#870
0.
#875
0"
1P
b1010000 Q
1.
#880
0.
#885
0P
1.
